swapi_client/__init__.py
swapi_client/client.py
swapi_client/exceptions.py
swapi_client/query_builder.py
swapi_client-0.2.4.dist-info/METADATA
swapi_client-0.2.4.dist-info/WHEEL
swapi_client-0.2.4.dist-info/licenses/LICENSE
swapi_client-0.2.4.dist-info/RECORD
