Metadata-Version: 2.4
Name: swapi-client
Version: 0.2.4
Summary: API client for Serwis Planner
Project-URL: Homepage, https://github.com/qwizi/swapi-client
Project-URL: Bug Tracker, https://github.com/qwizi/swapi-client/issues
Author-email: Adrian 'Qwizi' Ciołek <ciolek.adrian@proton.me>
License: MIT License
License-File: LICENSE
Requires-Python: >=3.12
Requires-Dist: httpx>=0.27.0
Requires-Dist: python-dotenv>=1.0.1
